tapestry/__init__.py
tapestry/__main__.py
tapestry/classes.py
tapestry/functions.py
tapestry-2.2.2.dist-info/LICENSE
tapestry-2.2.2.dist-info/METADATA
tapestry-2.2.2.dist-info/WHEEL
tapestry-2.2.2.dist-info/top_level.txt
tapestry-2.2.2.dist-info/RECORD
