Metadata-Version: 2.1
Name: tapestry
Version: 2.2.2
Summary: Tapestry Bespoke Backup Utility
Home-page: https://www.github.com/zadammac/Tapestry
Author: Zac Adam-MacEwen
Author-email: zadammac@arcanalabs.ca
License: UNKNOWN
Platform: UNKNOWN
License-File: LICENSE
Requires-Dist: keyring
Requires-Dist: paramiko
Requires-Dist: pysftp
Requires-Dist: python-gnupg
